{
  "cinnamon": [
    {
      "name": "manjaro-cinnamon-25.0.0-250527-linux612.iso",
      "size": 3684306944,
      "url": "https://files.manjaro.download/rc-202505270721/manjaro-cinnamon-25.0.0-250527-linux612.iso"
    },
    {
      "name": "manjaro-cinnamon-25.0.0-250527-linux612.iso.pkgs",
      "size": 21733,
      "url": "https://files.manjaro.download/rc-202505270721/manjaro-cinnamon-25.0.0-250527-linux612.iso.pkgs"
    },
    {
      "name": "manjaro-cinnamon-25.0.0-250527-linux612.iso.sha1",
      "size": 86,
      "url": "https://files.manjaro.download/rc-202505270721/manjaro-cinnamon-25.0.0-250527-linux612.iso.sha1"
    },
    {
      "name": "manjaro-cinnamon-25.0.0-250527-linux612.iso.sha256",
      "size": 110,
      "url": "https://files.manjaro.download/rc-202505270721/manjaro-cinnamon-25.0.0-250527-linux612.iso.sha256"
    },
    {
      "name": "manjaro-cinnamon-25.0.0-250527-linux612.iso.sha512",
      "size": 174,
      "url": "https://files.manjaro.download/rc-202505270721/manjaro-cinnamon-25.0.0-250527-linux612.iso.sha512"
    },
    {
      "name": "manjaro-cinnamon-25.0.0-250527-linux612.iso.sig",
      "size": 119,
      "url": "https://files.manjaro.download/rc-202505270721/manjaro-cinnamon-25.0.0-250527-linux612.iso.sig"
    }
  ],
  "gnome": [
    {
      "name": "manjaro-gnome-25.0.0-250527-linux612.iso",
      "size": 3918102528,
      "url": "https://files.manjaro.download/rc-202505270721/manjaro-gnome-25.0.0-250527-linux612.iso"
    },
    {
      "name": "manjaro-gnome-25.0.0-250527-linux612.iso.pkgs",
      "size": 22455,
      "url": "https://files.manjaro.download/rc-202505270721/manjaro-gnome-25.0.0-250527-linux612.iso.pkgs"
    },
    {
      "name": "manjaro-gnome-25.0.0-250527-linux612.iso.sha1",
      "size": 83,
      "url": "https://files.manjaro.download/rc-202505270721/manjaro-gnome-25.0.0-250527-linux612.iso.sha1"
    },
    {
      "name": "manjaro-gnome-25.0.0-250527-linux612.iso.sha256",
      "size": 107,
      "url": "https://files.manjaro.download/rc-202505270721/manjaro-gnome-25.0.0-250527-linux612.iso.sha256"
    },
    {
      "name": "manjaro-gnome-25.0.0-250527-linux612.iso.sha512",
      "size": 171,
      "url": "https://files.manjaro.download/rc-202505270721/manjaro-gnome-25.0.0-250527-linux612.iso.sha512"
    },
    {
      "name": "manjaro-gnome-25.0.0-250527-linux612.iso.sig",
      "size": 119,
      "url": "https://files.manjaro.download/rc-202505270721/manjaro-gnome-25.0.0-250527-linux612.iso.sig"
    }
  ],
  "i3": [
    {
      "name": "manjaro-i3-25.0.0-250527-linux612.iso",
      "size": 3632384000,
      "url": "https://files.manjaro.download/rc-202505270721/manjaro-i3-25.0.0-250527-linux612.iso"
    },
    {
      "name": "manjaro-i3-25.0.0-250527-linux612.iso.pkgs",
      "size": 20782,
      "url": "https://files.manjaro.download/rc-202505270721/manjaro-i3-25.0.0-250527-linux612.iso.pkgs"
    },
    {
      "name": "manjaro-i3-25.0.0-250527-linux612.iso.sha1",
      "size": 80,
      "url": "https://files.manjaro.download/rc-202505270721/manjaro-i3-25.0.0-250527-linux612.iso.sha1"
    },
    {
      "name": "manjaro-i3-25.0.0-250527-linux612.iso.sha256",
      "size": 104,
      "url": "https://files.manjaro.download/rc-202505270721/manjaro-i3-25.0.0-250527-linux612.iso.sha256"
    },
    {
      "name": "manjaro-i3-25.0.0-250527-linux612.iso.sha512",
      "size": 168,
      "url": "https://files.manjaro.download/rc-202505270721/manjaro-i3-25.0.0-250527-linux612.iso.sha512"
    },
    {
      "name": "manjaro-i3-25.0.0-250527-linux612.iso.sig",
      "size": 119,
      "url": "https://files.manjaro.download/rc-202505270721/manjaro-i3-25.0.0-250527-linux612.iso.sig"
    }
  ],
  "kde": [
    {
      "name": "manjaro-kde-25.0.0-250527-linux612.iso",
      "size": 4108124160,
      "url": "https://files.manjaro.download/rc-202505270721/manjaro-kde-25.0.0-250527-linux612.iso"
    },
    {
      "name": "manjaro-kde-25.0.0-250527-linux612.iso.pkgs",
      "size": 23900,
      "url": "https://files.manjaro.download/rc-202505270721/manjaro-kde-25.0.0-250527-linux612.iso.pkgs"
    },
    {
      "name": "manjaro-kde-25.0.0-250527-linux612.iso.sha1",
      "size": 81,
      "url": "https://files.manjaro.download/rc-202505270721/manjaro-kde-25.0.0-250527-linux612.iso.sha1"
    },
    {
      "name": "manjaro-kde-25.0.0-250527-linux612.iso.sha256",
      "size": 105,
      "url": "https://files.manjaro.download/rc-202505270721/manjaro-kde-25.0.0-250527-linux612.iso.sha256"
    },
    {
      "name": "manjaro-kde-25.0.0-250527-linux612.iso.sha512",
      "size": 169,
      "url": "https://files.manjaro.download/rc-202505270721/manjaro-kde-25.0.0-250527-linux612.iso.sha512"
    },
    {
      "name": "manjaro-kde-25.0.0-250527-linux612.iso.sig",
      "size": 119,
      "url": "https://files.manjaro.download/rc-202505270721/manjaro-kde-25.0.0-250527-linux612.iso.sig"
    }
  ],
  "sway": [
    {
      "name": "manjaro-sway-25.0.0-250527-linux612.iso",
      "size": 2968909824,
      "url": "https://files.manjaro.download/rc-202505270721/manjaro-sway-25.0.0-250527-linux612.iso"
    },
    {
      "name": "manjaro-sway-25.0.0-250527-linux612.iso.pkgs",
      "size": 14884,
      "url": "https://files.manjaro.download/rc-202505270721/manjaro-sway-25.0.0-250527-linux612.iso.pkgs"
    },
    {
      "name": "manjaro-sway-25.0.0-250527-linux612.iso.sha1",
      "size": 82,
      "url": "https://files.manjaro.download/rc-202505270721/manjaro-sway-25.0.0-250527-linux612.iso.sha1"
    },
    {
      "name": "manjaro-sway-25.0.0-250527-linux612.iso.sha256",
      "size": 106,
      "url": "https://files.manjaro.download/rc-202505270721/manjaro-sway-25.0.0-250527-linux612.iso.sha256"
    },
    {
      "name": "manjaro-sway-25.0.0-250527-linux612.iso.sha512",
      "size": 170,
      "url": "https://files.manjaro.download/rc-202505270721/manjaro-sway-25.0.0-250527-linux612.iso.sha512"
    },
    {
      "name": "manjaro-sway-25.0.0-250527-linux612.iso.sig",
      "size": 119,
      "url": "https://files.manjaro.download/rc-202505270721/manjaro-sway-25.0.0-250527-linux612.iso.sig"
    }
  ],
  "xfce": [
    {
      "name": "manjaro-xfce-25.0.0-250527-linux612.iso",
      "size": 3630112768,
      "url": "https://files.manjaro.download/rc-202505270721/manjaro-xfce-25.0.0-250527-linux612.iso"
    },
    {
      "name": "manjaro-xfce-25.0.0-250527-linux612.iso.pkgs",
      "size": 20906,
      "url": "https://files.manjaro.download/rc-202505270721/manjaro-xfce-25.0.0-250527-linux612.iso.pkgs"
    },
    {
      "name": "manjaro-xfce-25.0.0-250527-linux612.iso.sha1",
      "size": 82,
      "url": "https://files.manjaro.download/rc-202505270721/manjaro-xfce-25.0.0-250527-linux612.iso.sha1"
    },
    {
      "name": "manjaro-xfce-25.0.0-250527-linux612.iso.sha256",
      "size": 106,
      "url": "https://files.manjaro.download/rc-202505270721/manjaro-xfce-25.0.0-250527-linux612.iso.sha256"
    },
    {
      "name": "manjaro-xfce-25.0.0-250527-linux612.iso.sha512",
      "size": 170,
      "url": "https://files.manjaro.download/rc-202505270721/manjaro-xfce-25.0.0-250527-linux612.iso.sha512"
    },
    {
      "name": "manjaro-xfce-25.0.0-250527-linux612.iso.sig",
      "size": 119,
      "url": "https://files.manjaro.download/rc-202505270721/manjaro-xfce-25.0.0-250527-linux612.iso.sig"
    }
  ]
}
